vcap_utils/__init__.py
vcap_utils/version.py
vcap_utils/algorithms/__init__.py
vcap_utils/algorithms/distances.py
vcap_utils/algorithms/iou_cost_matrix.py
vcap_utils/algorithms/linear_assignment.py
vcap_utils/algorithms/nonmax_suppression.py
vcap_utils/backends/__init__.py
vcap_utils/backends/backend_rpc_process.py
vcap_utils/backends/base_encoder.py
vcap_utils/backends/base_openvino.py
vcap_utils/backends/base_tensorflow.py
vcap_utils/backends/crowd_density.py
vcap_utils/backends/depth.py
vcap_utils/backends/load_utils.py
vcap_utils/backends/openface_encoder.py
vcap_utils/backends/predictions.py
vcap_utils/backends/segmentation.py
vcap_utils/backends/tf_image_classification.py
vcap_utils/backends/tf_object_detection.py
vcap_utils-0.5.3.dist-info/METADATA
vcap_utils-0.5.3.dist-info/WHEEL
vcap_utils-0.5.3.dist-info/top_level.txt
vcap_utils-0.5.3.dist-info/RECORD
