Metadata-Version: 2.1
Name: vcap_utils
Version: 0.5.3
Summary: Utilities for creating OpenVisionCapsules easily in Python
Author: Aotu.ai
Classifier: Programming Language :: Python :: 3
Classifier: License :: OSI Approved :: BSD License
Classifier: Operating System :: OS Independent
Requires-Python: >=3.6
Requires-Dist: vcap
Provides-Extra: tests
Requires-Dist: pytest ; extra == 'tests'
Requires-Dist: mock ; extra == 'tests'
